multicast_dpi_system-1.1.1.dist-info/licenses/LICENSE
src/__init__.py
src/main.py
src/config_generator/__init__.py
src/config_generator/config_generator.py
src/config_generator/config_manager.py
src/config_generator/config_model.py
src/config_generator/factory.py
src/core/__init__.py
src/core/factory.py
src/core/flow_stats_manager.py
src/core/packet.py
src/core/packet_context.py
src/dpi_engine/__init__.py
src/dpi_engine/dpi_engine.py
src/dpi_engine/encrypted_analyzer.py
src/dpi_engine/protocol_identifier.py
src/dpi_engine/signature_matcher.py
src/interfaces/__init__.py
src/interfaces/config_generator.py
src/interfaces/dpi_engine.py
src/interfaces/packet_capture.py
src/interfaces/traffic_classifier.py
src/interfaces/policy_manager/policy_config.py
src/interfaces/policy_manager/policy_engine.py
src/interfaces/policy_manager/policy_manager.py
src/packet_capture/__init__.py
src/packet_capture/capture_system.py
src/packet_capture/filter_engine.py
src/packet_capture/multicast_listener.py
src/packet_capture/packet_buffer.py
src/policy_manager/__init__.py
src/policy_manager/factory.py
src/policy_manager/policy_config.py
src/policy_manager/policy_engine.py
src/policy_manager/policy_manager.py
src/policy_manager/policy_models.py
src/traffic_classifier/__init__.py
src/traffic_classifier/datamodels.py
src/traffic_classifier/flow_aware_classification.py
src/traffic_classifier/rule_classification.py
src/traffic_classifier/traffic_classifier.py
src/utils/__init__.py
src/utils/config_handler.py
src/utils/logging_utils.py
multicast_dpi_system-1.1.1.dist-info/METADATA
multicast_dpi_system-1.1.1.dist-info/WHEEL
multicast_dpi_system-1.1.1.dist-info/entry_points.txt
multicast_dpi_system-1.1.1.dist-info/top_level.txt
multicast_dpi_system-1.1.1.dist-info/RECORD
