Metadata-Version: 2.4
Name: multicast-dpi-system
Version: 1.1.1
Summary: A comprehensive Deep Packet Inspection (DPI) system designed for multicast traffic analysis with real-time policy enforcement and traffic classification
Author-email: Khushi Sikaria <khushisikaria1@gmail.com>
Maintainer-email: Khushi Sikaria <khushisikaria1@gmail.com>
License: MIT
Project-URL: Homepage, https://github.com/SikariaKhushi/Multicast_DPI_System.git
Project-URL: Documentation, https://multicast-dpi-system.readthedocs.io/
Project-URL: Repository, https://github.com/SikariaKhushi/Multicast_DPI_System.git
Project-URL: Bug Tracker, https://github.com/SikariaKhushi/Multicast_DPI_System.git/issues
Project-URL: Source Code, https://github.com/SikariaKhushi/Multicast_DPI_System.git
Keywords: dpi,multicast,network-analysis,traffic-classification,policy-enforcement,packet-capture,deep-packet-inspection
Classifier: Development Status :: 4 - Beta
Classifier: Intended Audience :: Developers
Classifier: Intended Audience :: System Administrators
Classifier: Intended Audience :: Telecommunications Industry
Classifier: License :: OSI Approved :: MIT License
Classifier: Operating System :: OS Independent
Classifier: Programming Language :: Python :: 3
Classifier: Programming Language :: Python :: 3.8
Classifier: Programming Language :: Python :: 3.9
Classifier: Programming Language :: Python :: 3.10
Classifier: Programming Language :: Python :: 3.11
Classifier: Programming Language :: Python :: 3.12
Classifier: Topic :: System :: Networking :: Monitoring
Classifier: Topic :: System :: Networking :: Firewalls
Classifier: Topic :: Communications
Classifier: Topic :: Software Development :: Libraries :: Python Modules
Requires-Python: >=3.8
License-File: LICENSE
Requires-Dist: dpkt>=1.9.8
Requires-Dist: pyshark>=0.6
Requires-Dist: scapy>=2.5.0
Requires-Dist: PyYAML>=6.0
Requires-Dist: psutil>=5.9.0
Requires-Dist: netifaces>=0.11.0
Provides-Extra: dev
Requires-Dist: pytest>=7.0.0; extra == "dev"
Requires-Dist: pytest-cov>=4.0.0; extra == "dev"
Requires-Dist: black>=23.0.0; extra == "dev"
Requires-Dist: flake8>=6.0.0; extra == "dev"
Requires-Dist: mypy>=1.0.0; extra == "dev"
Requires-Dist: pre-commit>=3.0.0; extra == "dev"
Provides-Extra: docs
Requires-Dist: sphinx>=6.0.0; extra == "docs"
Requires-Dist: sphinx-rtd-theme>=1.2.0; extra == "docs"
Requires-Dist: myst-parser>=1.0.0; extra == "docs"
Provides-Extra: test
Requires-Dist: pytest>=7.0.0; extra == "test"
Requires-Dist: pytest-cov>=4.0.0; extra == "test"
Requires-Dist: pytest-mock>=3.10.0; extra == "test"
Dynamic: license-file
